{
	"parent": "valley:exploration/deep_sea_eating",
	"display": {
		"title": {
			"text": "Salt Chuck Curer"
		},
		"icon": {
			"item": "valley:dried_sucker"
		},
		"description": {
			"text": "Cure some seafood"
		},
		"hidden": false
	},
	"criteria": {
		"dried_sucker": {
			"trigger": "minecraft:inventory_changed",
			"conditions": {
				"items": [
					{
						"items": [
							"valley:dried_sucker"
						]
					}
				]
			}
		},
		"dried_tropical_fish": {
			"trigger": "minecraft:inventory_changed",
			"conditions": {
				"items": [
					{
						"items": [
							"valley:dried_tropical_fish"
						]
					}
				]
			}
		},
		"dried_cod": {
			"trigger": "minecraft:inventory_changed",
			"conditions": {
				"items": [
					{
						"items": [
							"valley:dried_cod"
						]
					}
				]
			}
		},
		"fire_eel_dried": {
			"trigger": "minecraft:inventory_changed",
			"conditions": {
				"items": [
					{
						"items": [
							"valley:fire_eel_dried"
						]
					}
				]
			}
		},
		"dried_salmon": {
			"trigger": "minecraft:inventory_changed",
			"conditions": {
				"items": [
					{
						"items": [
							"valley:dried_salmon"
						]
					}
				]
			}
		}
	},
	"requirements": [
		[
			"dried_sucker"
		],
		[
			"dried_tropical_fish"
		],
		[
			"dried_cod"
		],
		[
			"dried_salmon"
		],
		[
			"fire_eel_dried"
		]
	]
}
